xagg2/__init__.py
xagg2/auxfuncs.py
xagg2/classes.py
xagg2/common.py
xagg2/core.py
xagg2/diag.py
xagg2/export.py
xagg2/options.py
xagg2/wrappers.py
xagg2/xagg2.py
xagg2-0.0.9.dist-info/LICENSE
xagg2-0.0.9.dist-info/METADATA
xagg2-0.0.9.dist-info/WHEEL
xagg2-0.0.9.dist-info/entry_points.txt
xagg2-0.0.9.dist-info/top_level.txt
xagg2-0.0.9.dist-info/RECORD
