Metadata-Version: 2.1
Name: xagg2
Version: 0.0.9
Summary: calculate weighted overlap or barely overlap for climate data
Author-email: advancehs <1019753743@qq.com>
License: MIT License
Project-URL: Homepage, https://github.com/advancehs/xagg2
Keywords: xagg2
Classifier: Intended Audience :: Developers
Classifier: License :: OSI Approved :: MIT License
Classifier: Natural Language :: English
Classifier: Programming Language :: Python :: 3.12
Requires-Python: >=3.8
License-File: LICENSE
Requires-Dist: numpy
Requires-Dist: pandas
Requires-Dist: matplotlib
Requires-Dist: xarray
Requires-Dist: geopandas
Requires-Dist: cartopy
Provides-Extra: all
Requires-Dist: xagg2[extra] ; extra == 'all'
Provides-Extra: extra
Requires-Dist: pandas ; extra == 'extra'
